rotalabs_redqueen/__init__.py
rotalabs_redqueen/_version.py
rotalabs_redqueen/cli.py
rotalabs_redqueen/core/__init__.py
rotalabs_redqueen/core/archive.py
rotalabs_redqueen/core/evolution.py
rotalabs_redqueen/core/fitness.py
rotalabs_redqueen/core/genome.py
rotalabs_redqueen/core/population.py
rotalabs_redqueen/core/selection.py
rotalabs_redqueen/llm/__init__.py
rotalabs_redqueen/llm/fitness.py
rotalabs_redqueen/llm/genome.py
rotalabs_redqueen/llm/judge.py
rotalabs_redqueen/llm/targets.py
rotalabs_redqueen-1.0.0.dist-info/METADATA
rotalabs_redqueen-1.0.0.dist-info/WHEEL
rotalabs_redqueen-1.0.0.dist-info/entry_points.txt
rotalabs_redqueen-1.0.0.dist-info/licenses/LICENSE
rotalabs_redqueen-1.0.0.dist-info/RECORD
