Metadata-Version: 2.4
Name: rotalabs-redqueen
Version: 1.0.0
Summary: Evolutionary adversarial testing framework - Quality-diversity evolution for AI safety research
Project-URL: Homepage, https://rotalabs.ai
Project-URL: Repository, https://github.com/rotalabs/rotalabs-redqueen
Project-URL: Documentation, https://rotalabs.github.io/rotalabs-redqueen/
Author-email: Subhadip Mitra <subhadip@rotalabs.ai>, Rotalabs Research <research@rotalabs.ai>
License-Expression: AGPL-3.0-or-later
License-File: LICENSE
Keywords: adversarial-testing,ai-safety,evolutionary-algorithms,llm-security,map-elites,quality-diversity,red-teaming
Classifier: Development Status :: 4 - Beta
Classifier: Intended Audience :: Developers
Classifier: Intended Audience :: Science/Research
Classifier: License :: OSI Approved :: GNU Affero General Public License v3 or later (AGPLv3+)
Classifier: Programming Language :: Python :: 3
Classifier: Programming Language :: Python :: 3.9
Classifier: Programming Language :: Python :: 3.10
Classifier: Programming Language :: Python :: 3.11
Classifier: Programming Language :: Python :: 3.12
Classifier: Topic :: Scientific/Engineering :: Artificial Intelligence
Classifier: Topic :: Security
Requires-Python: >=3.9
Requires-Dist: httpx>=0.25.0
Requires-Dist: numpy>=1.24.0
Requires-Dist: tqdm>=4.65.0
Provides-Extra: all
Requires-Dist: anthropic>=0.18.0; extra == 'all'
Requires-Dist: openai>=1.0.0; extra == 'all'
Provides-Extra: anthropic
Requires-Dist: anthropic>=0.18.0; extra == 'anthropic'
Provides-Extra: dev
Requires-Dist: black>=23.0.0; extra == 'dev'
Requires-Dist: mypy>=1.5.0; extra == 'dev'
Requires-Dist: pytest-asyncio>=0.21.0; extra == 'dev'
Requires-Dist: pytest-cov>=4.1.0; extra == 'dev'
Requires-Dist: pytest>=7.4.0; extra == 'dev'
Requires-Dist: ruff>=0.1.0; extra == 'dev'
Provides-Extra: docs
Requires-Dist: mkdocs-material>=9.4.0; extra == 'docs'
Requires-Dist: mkdocs>=1.5.0; extra == 'docs'
Requires-Dist: mkdocstrings[python]>=0.24.0; extra == 'docs'
Provides-Extra: llm
Requires-Dist: anthropic>=0.18.0; extra == 'llm'
Requires-Dist: openai>=1.0.0; extra == 'llm'
Provides-Extra: openai
Requires-Dist: openai>=1.0.0; extra == 'openai'
